docs/source/conf.py
examples/hi.py
pyspl/__init__.py
pyspl/character.py
pyspl/errors.py
pyspl/names.py
pyspl/operations.py
pyspl/play.py
py2spl-1.0.0.dist-info/METADATA
py2spl-1.0.0.dist-info/WHEEL
py2spl-1.0.0.dist-info/licenses/LICENSE
py2spl-1.0.0.dist-info/RECORD
